Metadata-Version: 1.0
Name: pywit-latest
Version: 5.1.0
Summary: Wit SDK for Python - No change from master branch
Home-page: http://github.com/wit-ai/pywit
Author: The Wit Team - Uploaded by Falcon
Author-email: help@wit.ai
License: UNKNOWN
Platform: UNKNOWN
